vym/__init__.py
vym/__main__.py
vym/__version__.py
vym/exceptions.py
vym/py.typed
vym/__pycache__/__init__.cpython-310.pyc
vym/__pycache__/__main__.cpython-310.pyc
vym/__pycache__/__version__.cpython-310.pyc
vym/__pycache__/exceptions.cpython-310.pyc
vym/configs/broot/conf.hjson
vym/configs/broot/dark-blue-skin.hjson
vym/configs/broot/dark-gruvbox.hjson
vym/configs/broot/dark-orange-skin.hjson
vym/configs/broot/solarized-dark.hjson
vym/configs/broot/solarized-light.hjson
vym/configs/broot/verbs.hjson
vym/configs/broot/white-skin.hjson
vym/configs/vym/vymrc
vym/configs/vym/vimrc.d/amix.vimrc
vym/configs/vym/vimrc.d/f2dv.vimrc
vym-0.0.1a2.dist-info/LICENSE
vym-0.0.1a2.dist-info/METADATA
vym-0.0.1a2.dist-info/WHEEL
vym-0.0.1a2.dist-info/entry_points.txt
vym-0.0.1a2.dist-info/top_level.txt
vym-0.0.1a2.dist-info/RECORD
