Metadata-Version: 2.1
Name: vym
Version: 0.0.1a2
Summary: WIP
Home-page: https://github.com/fresh2dev/vym
Author: Donald Mellenbruch
Author-email: hello@Fresh2.dev
Project-URL: Repository, https://github.com/fresh2dev/vym
Project-URL: Documentation, https://www.Fresh2.dev/code/r/vym/i
Project-URL: License, https://www.Fresh2.dev/code/r/vym/i/license
Project-URL: Issues, https://github.com/fresh2dev/vym/issues
Project-URL: Funding, https://www.Fresh2.dev/funding
Classifier: Programming Language :: Python :: 3
Requires-Python: >=3.7
License-File: LICENSE
Requires-Dist: yapx[shtab] (==0.0.1a17)
Requires-Dist: myke[io] (==0.0.1a18)
Requires-Dist: packaging (==23.*)
Requires-Dist: typing-extensions ; python_version < "3.10"
Provides-Extra: build
Requires-Dist: setuptools (>=62.3.0) ; extra == 'build'
Requires-Dist: build (==0.*) ; extra == 'build'
Requires-Dist: wheel (==0.*) ; extra == 'build'
Requires-Dist: twine (==4.*) ; extra == 'build'
Provides-Extra: dev
Requires-Dist: python-lsp-server[rope] (==1.*) ; extra == 'dev'
Requires-Dist: ruff (==0.*) ; extra == 'dev'
Requires-Dist: pyflyby (==1.*) ; extra == 'dev'
Requires-Dist: black (==22.*) ; extra == 'dev'
Requires-Dist: isort (==5.*) ; extra == 'dev'
Requires-Dist: mypy[reports] (==0.*) ; extra == 'dev'
Requires-Dist: pylint (==2.*) ; extra == 'dev'
Requires-Dist: pylint-pytest (==1.*) ; extra == 'dev'
Provides-Extra: docs
Requires-Dist: mkdocs (==1.*) ; extra == 'docs'
Requires-Dist: mkdocstrings[python] (==0.19.*) ; extra == 'docs'
Requires-Dist: mkdocs-autorefs (==0.*) ; extra == 'docs'
Provides-Extra: tests
Requires-Dist: pytest (==7.*) ; extra == 'tests'
Requires-Dist: pytest-cov (==4.*) ; extra == 'tests'
Requires-Dist: pytest-html (==3.*) ; extra == 'tests'
Requires-Dist: pytest-sugar (==0.*) ; extra == 'tests'
Requires-Dist: pylint (==2.*) ; extra == 'tests'
Requires-Dist: pylint-pytest (==1.*) ; extra == 'tests'
Requires-Dist: packaging (==23.*) ; extra == 'tests'
Requires-Dist: mocx (==0.0.1a1) ; extra == 'tests'
